CHANGELOG.txt
LICENCE.txt
MANIFEST.in
README.txt
setup.py
hafezpoem/__init__.py
hafezpoem/poems.csv
hafezpoem.egg-info/PKG-INFO
hafezpoem.egg-info/SOURCES.txt
hafezpoem.egg-info/dependency_links.txt
hafezpoem.egg-info/top_level.txt