Metadata-Version: 1.1
Name: hafezpoem
Version: 1.0.6
Summary: Random poem of hafez for restaurant factor and other staff
Home-page: UNKNOWN
Author: Radesh Farokhmanesh
Author-email: radesh.farokhmanesh@gmail.com
License: MIT
Keywords: hafez fal poem factor restaurant
Platform: UNKNOWN
Classifier: Development Status :: 5 - Production/Stable
Classifier: Intended Audience :: Developers
Classifier: Operating System :: Microsoft :: Windows :: Windows 10
Classifier: License :: OSI Approved :: MIT License
Classifier: Programming Language :: Python :: 3
